MANIFEST.in
README.md
setup.py
examples/LINTools_example.py
examples/MasterSimulation.py
examples/SlaveSimulation.py
tests/LDF_parser_test.py
tests/LUC_test.py
ucanlintools/LDF_parser.py
ucanlintools/LINFrame.py
ucanlintools/LUC.py
ucanlintools/__init__.py
ucanlintools/ldf.lark
ucanlintools.egg-info/PKG-INFO
ucanlintools.egg-info/SOURCES.txt
ucanlintools.egg-info/dependency_links.txt
ucanlintools.egg-info/requires.txt
ucanlintools.egg-info/top_level.txt