Metadata-Version: 2.1
Name: ucanlintools
Version: 0.0.8
Summary: Local Interconnect Network (LIN) support for python
Home-page: https://github.com/uCAN-LIN/LinUSBConverter
Author: ucan
Author-email: ucandevices@mail.com
License: MIT
Project-URL: Documentation, https://ucandevices.github.io/
Project-URL: Source Code, https://github.com/uCAN-LIN/LinUSBConverter/tree/master/python_lib
Keywords: LIN,LDF,LUC,uCAN,parser
Platform: UNKNOWN
Classifier: Programming Language :: Python :: 3
Classifier: License :: OSI Approved :: MIT License
Classifier: Operating System :: OS Independent
